{"oosElement":".cta-with-price button.out-stock","priceElement":".sub-menu-price-panel .cost","stores":[{"name":"Razer United States Online Store","url":"https://www.razer.com/"},{"name":"Razer Canada Online Store","url":"https://www.razer.com/ca-en/"},{"name":"Razer Belgium Online Store","url":"https://www.razer.com/eu-en/"},{"name":"Razer Latvia Online Store","url":"https://www2.razer.com/eu-en/"},{"name":"Razer Bulgaria Online Store","url":"https://www2.razerzone.com/eu-en/"},{"name":"Razer Luxembourg Online Store","url":"https://www.razer.com/eu-en/"},{"name":"Razer Croatia Online Store","url":"https://www2.razerzone.com/eu-en/"},{"name":"Razer Malta Online Store","url":"https://www2.razer.com/eu-en/"},{"name":"Razer Cyprus Online Store","url":"https://www2.razer.com/eu-en/"},{"name":"Razer Netherlands Online Store","url":"https://www.razer.com/eu-en/"},{"name":"Razer Czech Republic Online Store","url":"https://www2.razer.com/eu-en/"},{"name":"Razer Norway Online Store","url":"https://www.razer.com/eu-en/"},{"name":"Razer Denmark Online Store","url":"https://www.razer.com/eu-en/"},{"name":"Razer Österreich (Austria) Online Store","url":"https://www.razer.com/de-de/"},{"name":"Razer Deutschland (Germany) Online Store","url":"https://www.razer.com/de-de/"},{"name":"Razer Poland Online Store","url":"https://www.razer.com/eu-en/"},{"name":"Razer España (Spain) Online Store","url":"https://www2.razer.com/es-es/"},{"name":"Razer Portugal Online Store","url":"https://www.razer.com/eu-en/"},{"name":"Razer Estonia Online Store","url":"https://www2.razer.com/eu-en/"},{"name":"Razer Россия (Russia) Online Store","url":"https://www.razer.ru/"},{"name":"Razer Finland Online Store","url":"https://www.razer.com/eu-en/"},{"name":"Razer Romania Online Store","url":"https://www2.razerzone.com/eu-en/"},{"name":"Razer France Online Store","url":"https://www.razer.com/fr-fr/"},{"name":"Razer Slovakia Online Store","url":"https://www2.razer.com/eu-en/"},{"name":"Razer Greece Online Store","url":"https://www2.razer.com/eu-en/"},{"name":"Razer Slovenia Online Store","url":"https://www2.razer.com/eu-en/"},{"name":"Razer Hungary Online Store","url":"https://www2.razerzone.com/eu-en/"},{"name":"Razer Sweden Online Store","url":"https://www.razer.com/eu-en/"},{"name":"Razer Ireland Online Store","url":"https://www.razer.com/eu-en/"},{"name":"Razer United Kingdom Online Store","url":"https://www.razer.com/gb-en/"},{"name":"Razer Italia (Italy) Online Store","url":"https://www2.razer.com/it-it/"},{"name":"Razer Europe-English Online Store","url":"https://www.razer.com/eu-en/"},{"name":"Razer Australia Online Store","url":"https://www2.razer.com/au-en/"},{"name":"Razer Japan Online Store","url":"https://www2.razer.com/jp-jp/"},{"name":"Razer Malaysia Online Store","url":"https://www2.razer.com/ap-en/"},{"name":"Razer New Zealand Online Store","url":"https://www2.razer.com/ap-en/"},{"name":"Razer Philippines Online Store","url":"https://www2.razer.com/ap-en/"},{"name":"Razer Singapore Online Store","url":"https://www.razer.com/sg-en/"},{"name":"Razer Thailand Online Store","url":"https://www2.razer.com/ap-en/"},{"name":"Razer English (Hong Kong) Online Store","url":"https://www.razer.com/hk-en/"},{"name":"Razer Traditional Chinese (Hong Kong) Online Store","url":"https://www.razer.com/hk-zh/"},{"name":"Razer 中国 (China) Online Store","url":"http://cn.razerzone.com/"},{"name":"Razer 臺灣 (Taiwan) Online Store","url":"https://www2.razer.com/tw-zh/"},{"name":"Razer 대한민국 (South Korea) Online Store","url":"https://www2.razer.com/kr-kr/"}]}